merger/__init__.py
merger/cli.py
merger/exceptions/__init__.py
merger/exceptions/exceptions.py
merger/file_tree/__init__.py
merger/file_tree/entry.py
merger/file_tree/tree.py
merger/file_tree/type.py
merger/file_tree/exporters/__init__.py
merger/file_tree/exporters/directory_tree_exporter.py
merger/file_tree/exporters/json_exporter.py
merger/file_tree/exporters/json_tree_exporter.py
merger/file_tree/exporters/plain_text_exporter.py
merger/file_tree/exporters/strategy.py
merger/file_tree/exporters/tree_exporter.py
merger/file_tree/exporters/tree_with_plain_text_exporter.py
merger/logging/__init__.py
merger/logging/logger.py
merger/parsing/__init__.py
merger/parsing/default_parser.py
merger/parsing/modules.py
merger/parsing/parser.py
merger/parsing/parsers.py
merger/resources/__init__.py
merger/resources/ignore_files/__init__.py
merger/resources/ignore_files/default.ignore
merger/resources/ignore_files/java.ignore
merger/resources/ignore_files/node.ignore
merger/resources/ignore_files/python.ignore
merger/utils/__init__.py
merger/utils/config.py
merger/utils/default_ignore_files.py
merger/utils/files.py
merger/utils/hash.py
merger/utils/json.py
merger/utils/merger_dir.py
merger/utils/patterns.py
merger/utils/version.py
merger_cli-2.4.4.dist-info/licenses/LICENSE
merger_cli-2.4.4.dist-info/METADATA
merger_cli-2.4.4.dist-info/WHEEL
merger_cli-2.4.4.dist-info/entry_points.txt
merger_cli-2.4.4.dist-info/top_level.txt
merger_cli-2.4.4.dist-info/RECORD
