Metadata-Version: 2.4
Name: merger-cli
Version: 2.4.4
Summary: Merger is a tool that scans a directory, filters files using customizable patterns, and merges readable content into a single output file.
Author-email: Diogo Toporcov <diogotoporcov@gmail.com>
License-Expression: MIT
Project-URL: Homepage, https://github.com/diogotoporcov/merger-cli
Project-URL: Documentation, https://github.com/diogotoporcov/merger-cli
Keywords: merger,file system,concatenation,automation,development
Classifier: Programming Language :: Python :: 3
Classifier: Operating System :: OS Independent
Classifier: Intended Audience :: Developers
Classifier: Topic :: Software Development :: Libraries :: Python Modules
Requires-Python: >=3.8
License-File: LICENSE
Requires-Dist: chardet>=5.2.0
Requires-Dist: filetype>=1.2.0
Dynamic: license-file
